{
  "slug": "tributacion",
  "url": "https://fce.unl.edu.ar/tributacion/",
  "strategy": "fce-microsite",
  "content_hash": "f2e5f0f3329327b40d45438b5e891403acf452aa7a41b420acbe061b1bbf95be",
  "previous_hash": null,
  "pages_count": 13,
  "pages": [
    {
      "url": "https://fce.unl.edu.ar/tributacion/",
      "title": "INFORMACIÓN DE INTERÉS",
      "length": 851
    },
    {
      "url": "https://www.fce.unl.edu.ar/tributacion/index.php?act=showSubcategoria&id=172",
      "title": "Presentación de la carrera",
      "length": 1662
    },
    {
      "url": "https://www.fce.unl.edu.ar/tributacion/index.php?act=showSubcategoria&id=142",
      "title": "Duración de la carrera",
      "length": 1139
    },
    {
      "url": "https://www.fce.unl.edu.ar/tributacion/index.php?act=showSubcategoria&id=143",
      "title": "Días y horarios de cursado",
      "length": 1056
    },
    {
      "url": "https://www.fce.unl.edu.ar/tributacion/index.php?act=showSubcategoria&id=144",
      "title": "Cursado y evaluación",
      "length": 1499
    },
    {
      "url": "https://www.fce.unl.edu.ar/tributacion/index.php?act=showCategoria&id=194",
      "title": "Informes e Inscripción",
      "length": 1796
    },
    {
      "url": "https://www.fce.unl.edu.ar/tributacion/index.php?act=showSubcategoria&id=153",
      "title": "Estructura del Plan de Estudio",
      "length": 2181
    },
    {
      "url": "https://www.fce.unl.edu.ar/tributacion/index.php?act=showSubcategoria&id=148",
      "title": "Detalle de las Asignaturas",
      "length": 19187
    },
    {
      "url": "https://www.fce.unl.edu.ar/tributacion/index.php?act=showSubcategoria&id=152",
      "title": "Cursos de Posgrado",
      "length": 1381
    },
    {
      "url": "https://www.fce.unl.edu.ar/tributacion/index.php?act=showSubcategoria&id=180",
      "title": "Objetivos curriculares",
      "length": 2274
    },
    {
      "url": "https://www.fce.unl.edu.ar/tributacion/index.php?act=showSubcategoria&id=151",
      "title": "Comité Académico",
      "length": 1331
    },
    {
      "url": "https://www.fce.unl.edu.ar/tributacion/index.php?act=showSubcategoria&id=167",
      "title": "Conducción de la carrera",
      "length": 1940
    },
    {
      "url": "https://www.fce.unl.edu.ar/tributacion/index.php?act=showSubcategoria&id=149",
      "title": "Docentes de la carrera",
      "length": 2204
    }
  ],
  "scraped_at": "2026-05-18T20:15:19.858Z",
  "last_checked_at": "2026-05-18T20:15:19.858Z"
}
